NeonLove/__init__.py
NeonLove/neonlove_class.py
NeonLove-0.0.1.dist-info/METADATA
NeonLove-0.0.1.dist-info/WHEEL
NeonLove-0.0.1.dist-info/top_level.txt
NeonLove-0.0.1.dist-info/RECORD
