Metadata-Version: 2.1
Name: NeonLove
Version: 0.0.1
Summary: Show your love in neon way.
Home-page: https://github.com/Gri72/NeonLove
Author: Gri72
Author-email: grirow@yandex.ru
Project-URL: GitHub, https://github.com/Gri72/NeonLove
Keywords: love neon
Classifier: Programming Language :: Python :: 3.9
Classifier: License :: OSI Approved :: MIT License
Classifier: Operating System :: OS Independent
Requires-Python: >=3.9
Requires-Dist: matplotlib
Requires-Dist: numpy
